managed_account_client.py
secret_client.py
secrets_safe_library/__init__.py
secrets_safe_library/authentication.py
secrets_safe_library/cert_util.py
secrets_safe_library/exceptions.py
secrets_safe_library/managed_account.py
secrets_safe_library/secrets.py
secrets_safe_library/secrets_safe.py
secrets_safe_library/utils.py
test_secrets_safe_library_bt-1.0.dist-info/LICENSE
test_secrets_safe_library_bt-1.0.dist-info/METADATA
test_secrets_safe_library_bt-1.0.dist-info/WHEEL
test_secrets_safe_library_bt-1.0.dist-info/top_level.txt
test_secrets_safe_library_bt-1.0.dist-info/RECORD
